paleoveg/__init__.py
paleoveg/model_loader.py
paleoveg/predictor.py
PaleoVeg-0.1.2.dist-info/LICENSE
PaleoVeg-0.1.2.dist-info/METADATA
PaleoVeg-0.1.2.dist-info/WHEEL
PaleoVeg-0.1.2.dist-info/top_level.txt
PaleoVeg-0.1.2.dist-info/RECORD
