Metadata-Version: 2.1
Name: PaleoVeg
Version: 0.1.2
Summary: Predict paleovegetation from bioclimatic variables.
Home-page: https://github.com/roink/PaleoVeg
Author: Philipp Schlüter
Author-email: p.schlueter@uni-koeln.de
Classifier: Programming Language :: Python :: 3
Classifier: License :: OSI Approved :: MIT License
Classifier: Operating System :: OS Independent
Requires-Python: >=3.7
License-File: LICENSE
Requires-Dist: cartopy
Requires-Dist: joblib
Requires-Dist: matplotlib
Requires-Dist: numpy >=2.1.3
Requires-Dist: pandas >=2.2.3
Requires-Dist: requests
Requires-Dist: scikit-learn >=1.5.2
